adult/__init__.py
adult/adult.py
adult/adult_raw.py
adult_dataset-3.0.0.dist-info/LICENSE
adult_dataset-3.0.0.dist-info/WHEEL
adult_dataset-3.0.0.dist-info/METADATA
adult_dataset-3.0.0.dist-info/RECORD
