Metadata-Version: 2.1
Name: adult-dataset
Version: 3.0.0
Summary: PyTorch dataset wrapper for the
Keywords: PyTorch,dataset,Adult,Census Income
Author-email: David Boetius <david.boetius@uni-konstanz.de>
Requires-Python: >=3.9
Classifier: Programming Language :: Python :: 3
Classifier: License :: OSI Approved :: MIT License
Classifier: Operating System :: OS Independent
Requires-Dist: torch >=1.9, <3.0
Requires-Dist: numpy >=1.20, <2.0
Requires-Dist: pandas >=2.1, <3.0
Requires-Dist: requests >=2.25, <3.0
Requires-Dist: flit==3.9.0 ; extra == "develop"
Requires-Dist: black==23.7.0 ; extra == "develop"
Requires-Dist: pytest >=7.4, <8.0 ; extra == "test"
Requires-Dist: nox==2023.4.22 ; extra == "test"
Project-URL: Bug Tracker, https://github.com/cherrywoods/adult-dataset/issues
Project-URL: Homepage, https://github.com/cherrywoods/adult-dataset
Project-URL: Repository, https://github.com/cherrywoods/adult-dataset.git
Provides-Extra: develop
Provides-Extra: test
